t_tech/invest/__init__.py
t_tech/invest/_error_hub.py
t_tech/invest/_errors.py
t_tech/invest/_grpc_helpers.py
t_tech/invest/async_services.py
t_tech/invest/caching/__init__.py
t_tech/invest/caching/instruments_cache/__init__.py
t_tech/invest/caching/instruments_cache/instrument_storage.py
t_tech/invest/caching/instruments_cache/instruments_cache.py
t_tech/invest/caching/instruments_cache/interface.py
t_tech/invest/caching/instruments_cache/models.py
t_tech/invest/caching/instruments_cache/protocol.py
t_tech/invest/caching/instruments_cache/settings.py
t_tech/invest/caching/market_data_cache/__init__.py
t_tech/invest/caching/market_data_cache/cache.py
t_tech/invest/caching/market_data_cache/cache_settings.py
t_tech/invest/caching/market_data_cache/datetime_range.py
t_tech/invest/caching/market_data_cache/instrument_date_range_market_data.py
t_tech/invest/caching/market_data_cache/instrument_market_data_storage.py
t_tech/invest/caching/market_data_cache/interface.py
t_tech/invest/caching/market_data_cache/serialization.py
t_tech/invest/caching/overrides.py
t_tech/invest/candle_getter_protocol.py
t_tech/invest/channels.py
t_tech/invest/clients.py
t_tech/invest/constants.py
t_tech/invest/exceptions.py
t_tech/invest/grpc/__init__.py
t_tech/invest/grpc/common_pb2.py
t_tech/invest/grpc/common_pb2.pyi
t_tech/invest/grpc/common_pb2_grpc.py
t_tech/invest/grpc/google/api/field_behavior_pb2.py
t_tech/invest/grpc/google/api/field_behavior_pb2.pyi
t_tech/invest/grpc/google/api/field_behavior_pb2_grpc.py
t_tech/invest/grpc/instruments_pb2.py
t_tech/invest/grpc/instruments_pb2.pyi
t_tech/invest/grpc/instruments_pb2_grpc.py
t_tech/invest/grpc/marketdata_pb2.py
t_tech/invest/grpc/marketdata_pb2.pyi
t_tech/invest/grpc/marketdata_pb2_grpc.py
t_tech/invest/grpc/operations_pb2.py
t_tech/invest/grpc/operations_pb2.pyi
t_tech/invest/grpc/operations_pb2_grpc.py
t_tech/invest/grpc/orders_pb2.py
t_tech/invest/grpc/orders_pb2.pyi
t_tech/invest/grpc/orders_pb2_grpc.py
t_tech_investments-0.3.3.dist-info/LICENSE
t_tech_investments-0.3.3.dist-info/METADATA
t_tech_investments-0.3.3.dist-info/WHEEL
t_tech_investments-0.3.3.dist-info/RECORD
